src/__init__.py
src/homedir.py
cli_app_directory-0.1.dist-info/LICENCE
cli_app_directory-0.1.dist-info/METADATA
cli_app_directory-0.1.dist-info/WHEEL
cli_app_directory-0.1.dist-info/top_level.txt
cli_app_directory-0.1.dist-info/RECORD
